goodmap/__init__.py
goodmap/admin_api.py
goodmap/api_models.py
goodmap/clustering.py
goodmap/config.py
goodmap/core.py
goodmap/core_api.py
goodmap/data_models/location.py
goodmap/data_validator.py
goodmap/db.py
goodmap/exceptions.py
goodmap/formatter.py
goodmap/goodmap.py
goodmap/json_security.py
goodmap/templates/goodmap-admin.html
goodmap/templates/map.html
goodmap-1.4.0.dist-info/LICENSE.md
goodmap-1.4.0.dist-info/METADATA
goodmap-1.4.0.dist-info/WHEEL
goodmap-1.4.0.dist-info/RECORD
