Metadata-Version: 2.3
Name: goodmap
Version: 1.4.0
Summary: Map engine to serve all the people :)
Author: Krzysztof Kolodzinski
Author-email: krzysztof.kolodzinski@problematy.pl
Requires-Python: >=3.10,<4.0
Classifier: Programming Language :: Python :: 3
Classifier: Programming Language :: Python :: 3.10
Classifier: Programming Language :: Python :: 3.11
Classifier: Programming Language :: Python :: 3.12
Classifier: Programming Language :: Python :: 3.13
Provides-Extra: docs
Requires-Dist: Babel (>=2.10.3,<3.0.0)
Requires-Dist: Flask (==3.0.3)
Requires-Dist: Flask-Babel (>=4.0.0,<5.0.0)
Requires-Dist: Flask-WTF (>=1.2.1,<2.0.0)
Requires-Dist: PyYAML (>=6.0,<7.0)
Requires-Dist: aiohttp (>=3.8.4,<4.0.0)
Requires-Dist: deprecation (>=2.1.0,<3.0.0)
Requires-Dist: google-cloud-storage (>=2.7.0,<3.0.0)
Requires-Dist: gql (>=3.4.0,<4.0.0)
Requires-Dist: gunicorn (>=20.1,<24.0)
Requires-Dist: humanize (>=4.6.0,<5.0.0)
Requires-Dist: myst-parser (>=4.0.0,<5.0.0) ; extra == "docs"
Requires-Dist: numpy (>=2.2.0,<3.0.0)
Requires-Dist: platzky (>=1.3.0,<2.0.0)
Requires-Dist: pydantic (>=2.7.1,<3.0.0)
Requires-Dist: pysupercluster-problematy (>=0.7.8,<0.8.0)
Requires-Dist: scipy (>=1.15.1,<2.0.0)
Requires-Dist: spectree (>=2.0.1,<3.0.0)
Requires-Dist: sphinx (>=8.0.0,<9.0.0) ; extra == "docs"
Requires-Dist: sphinx-rtd-theme (>=3.0.0,<4.0.0) ; extra == "docs"
Requires-Dist: tomli (>=2.0.0,<3.0.0) ; extra == "docs"
